ewii/EwiiError.py
ewii/Settings.py
ewii/__init__.py
ewii-0.2.1.dist-info/METADATA
ewii-0.2.1.dist-info/WHEEL
ewii-0.2.1.dist-info/top_level.txt
ewii-0.2.1.dist-info/RECORD
