Metadata-Version: 2.4
Name: ewii
Version: 0.2.1
Summary: A Python client for EWIIs self-service portal
Home-page: https://github.com/brandonbondig/ewii-python
Author: Brandon Bondig
Author-email: brandon@bondig.dk
Classifier: Programming Language :: Python :: 3
Classifier: License :: OSI Approved :: MIT License
Classifier: Operating System :: OS Independent
Requires-Python: >=3.7
Requires-Dist: requests
Requires-Dist: fastapi
Requires-Dist: rich
Requires-Dist: beautifulsoup4
Requires-Dist: playwright
Requires-Dist: pydantic-settings
